setup.py
hml_equation_parser/__init__.py
hml_equation_parser/config.json
hml_equation_parser/convertMap.json
hml_equation_parser/hmlParser.py
hml_equation_parser/hulkEqParser.py
hml_equation_parser/hulkReplaceMethod.py
hml_equation_parser.egg-info/PKG-INFO
hml_equation_parser.egg-info/SOURCES.txt
hml_equation_parser.egg-info/dependency_links.txt
hml_equation_parser.egg-info/requires.txt
hml_equation_parser.egg-info/top_level.txt