Metadata-Version: 1.1
Name: hml-equation-parser
Version: 1.0.12
Summary: Convert eqaution string in hml to latex string.
Home-page: https://github.com/OpenBapul/hml-equation-parser
Author: Hyeongseok.Oh.hulk
Author-email: snuboy89@gmail.com
License: UNKNOWN
Platform: UNKNOWN
Classifier: Development Status :: 5 - Production/Stable
Classifier: Environment :: Console
Classifier: Intended Audience :: Developers
Classifier: License :: OSI Approved :: Apache Software License
Classifier: Programming Language :: Python :: 3.5
